comfy_api_simplified/__init__.py
comfy_api_simplified/comfy_api_wrapper.py
comfy_api_simplified/comfy_workflow_wrapper.py
comfy_api_simplified-1.4.2.dist-info/METADATA
comfy_api_simplified-1.4.2.dist-info/WHEEL
comfy_api_simplified-1.4.2.dist-info/licenses/LICENSE
comfy_api_simplified-1.4.2.dist-info/RECORD
