Metadata-Version: 2.4
Name: comfy_api_simplified
Version: 1.4.2
Summary: A simple way to schedule ComfyUI prompts with different parameters
Project-URL: Homepage, https://github.com/deimos-deimos/comfy_api_simplified
Project-URL: Issues, https://github.com/deimos-deimos/comfy_api_simplified/issues
Author-email: Deimos Deimos <deimos.double@gmail.com>
License-File: LICENSE
Classifier: License :: OSI Approved :: MIT License
Classifier: Operating System :: OS Independent
Classifier: Programming Language :: Python :: 3
Requires-Python: >=3.8
Requires-Dist: requests
